abilian/__init__.py
abilian/crm/__init__.py
abilian/crm/excel/__init__.py
abilian/crm/excel/columns/__init__.py
abilian/crm/excel/columns/base.py
abilian/crm/excel/columns/dates.py
abilian/crm/excel/columns/misc.py
abilian/crm/excel/columns/postaladdress.py
abilian/crm/excel/columns/related.py
abilian/crm/excel/columns/tags.py
abilian/crm/excel/columns/vocabulary.py
abilian/crm/excel/columns/yearly.py
abilian/crm/excel/exc.py
abilian/crm/excel/manager.py
abilian/crm/excel/tasks.py
abilian/crm/excel/util.py
abilian/crm/excel/views.py
abilian/crm/extension.py
abilian/crm/forms.py
abilian/crm/generator/__init__.py
abilian/crm/generator/autoname.py
abilian/crm/generator/codegen.py
abilian/crm/generator/definitions.py
abilian/crm/generator/fieldtypes/__init__.py
abilian/crm/generator/fieldtypes/base.py
abilian/crm/generator/fieldtypes/entity.py
abilian/crm/generator/fieldtypes/formfields.py
abilian/crm/generator/fieldtypes/phonenumber.py
abilian/crm/generator/fieldtypes/postaladdress.py
abilian/crm/generator/fieldtypes/registry.py
abilian/crm/generator/fieldtypes/simple.py
abilian/crm/generator/fieldtypes/tests.py
abilian/crm/generator/fieldtypes/vocabulary.py
abilian/crm/generator/fieldtypes/yearly.py
abilian/crm/generator/module.py
abilian/crm/jinja_filters.py
abilian/crm/models.py
abilian/crm/static/js/async_export.js
abilian/crm/templates/crm/excel/async_export.html
abilian/crm/templates/crm/widgets/macros.html
abilian/crm/templates/crm/widgets/phonenumber_fieldlist.html
abilian/crm/templates/crm/widgets/phonenumber_fieldlist_view.html
abilian/crm/templates/crm/widgets/phonenumber_model_edit.html
abilian/crm/templates/crm/widgets/phonenumber_model_view.html
abilian/crm/tests/__init__.py
abilian/crm/tests/test_jinja_filters.py
abilian/crm/translations/en/LC_MESSAGES/messages.po
abilian/crm/translations/fr/LC_MESSAGES/messages.po
abilian/crm/translations/messages.pot
abilian/crm/widgets.py
abilian_crm_core-0.1.28.dist-info/WHEEL
abilian_crm_core-0.1.28.dist-info/METADATA
abilian_crm_core-0.1.28.dist-info/RECORD
